Workbook

Sheet Expenses
A2: Expenses | B2: Fortnight | C2: Month | D2: Year | F2: Expenses | G2: Fortnight | H2: Month | I2: Year | K2: Expenses | L2: Fortnight | M2: Month | N2: Year | P2: Expenses | Q2: Fortnight | R2: Month | S2: Year | U2: Expenses | V2: Fortnight | W2: Month | X2: Year
A3: Groceries & Food | B3: 1000 | C3: =B3*26/12 -> 2166.6667 | D3: =B3*26 -> 26000 | F3: Home loan | G3: =I3/26 -> 2943.2308 | H3: =6377 -> 6377 | I3: =H3*12 -> 76524 | K3: Home insurance | L3: =N3/26 -> 106.44462 | M3: 230.63 | N3: =M3*12 -> 2767.56 | P3: Electricity | Q3: =S3/26 -> 161.53846 | R3: 350 | S3: =R3*12 -> 4200 | U3: Ford Ranger rego | V3: =X3/26 -> 38.615385 | W3: =X3/12 -> 83.666667 | X3: =1004 -> 1004
A4: House Maintenance | B4: 100 | C4: =D4/12 -> 216.66667 | D4: =B4*26 -> 2600 | K4: Internet | L4: =M4*12/26 -> 32.307692 | M4: 70 | N4: =M4*12 -> 840 | P4: Gas | Q4: =S4/26 -> 25.384615 | R4: 55 | S4: =R4*12 -> 660 | U4: Ford Ranger insurance | V4: =X4/26 -> 0 | W4: =X4/12 -> 0 | X4: 0
A5: Clothing & Footwear | B5: 100 | C5: =D5/12 -> 216.66667 | D5: =B5*26 -> 2600 | K5: Phone & Mobile Data | L5: =M5*12/26 -> 27.692308 | M5: =20+20+20 -> 60 | N5: =L5*26 -> 720 | P5: Rates | Q5: =S5/26 -> 91.230769 | R5: =593/3 -> 197.66667 | S5: =R5*12 -> 2372
A6: Cosmetics | B6: =D6/26 -> 61.538462 | C6: =400 / 3 -> 133.33333 | D6: =C6*12 -> 1600 | K6: iCloud | L6: 2.5 | M6: =14.99 -> 14.99 | N6: =M6*12 -> 179.88 | P6: Water & Sewage | Q6: =S6/26 -> 84.615385 | R6: =550/3 -> 183.33333 | S6: =R6*12 -> 2200
A7: Personal care | B7: 150 | C7: =D7/12 -> 325 | D7: =B7*26 -> 3900 | K7: Flick Pest Control | L7: =M7*12/26 -> 22.615385 | M7: 49 | N7: =M7*12 -> 588
A8: Dinning out | B8: 120 | C8: =D8/12 -> 260 | D8: =B8*26 -> 3120 | K8: Pet Insurance (Dogs) | L8: =M8*12/26 -> 31.412308 | M8: 68.06 | N8: =M8*12 -> 816.72
A9: Work clothes Tess | B9: 100 | C9: =D9/12 -> 216.66667 | D9: =B9*26 -> 2600 | K9: Ford Ranger maintenance | L9: =N9/26 -> 46.153846 | M9: =N9/12 -> 100 | N9: 1200
K10: HBO Max
K11: Netflix | L11: =N11/26 -> 9.6876923 | M11: 20.99 | N11: =M11*12 -> 251.88
K12: Spotify | L12: =N12/26 -> 9.6876923 | M12: 20.99 | N12: =M12*12 -> 251.88
K13: Disney+ | L13: =N13/26 -> 7.38 | M13: 15.99 | N13: =M13*12 -> 191.88
K14: Binge
K15: Amazon Prime | L15: =M15*12/26 -> 4.4184615 | M15: =N15/12+2.99 -> 9.5733333 | N15: =79 -> 79
K16: Paramount+ | L16: =N16/26 -> 5.9953846 | M16: 12.99 | N16: =M16*12 -> 155.88
K17: Heyu | L17: =N17/26 -> 4.1492308 | M17: 8.99 | N17: =M17*12 -> 107.88
K18: Private Health Insurance | L18: =M18*12/26 -> 87.881538 | M18: 190.41 | N18: =M18*12 -> 2284.92
K19: Daycare | L19: =163.9 * 10 * 0.5006 -> 820.4834 | M19: =N19/12 -> 1777.714 | N19: =L19*26 -> 21332.568
K20: YMCA | L20: =35.88 * 10 * 0.5006 -> 179.61528 | M20: =N20/12 -> 389.16644 | N20: =L20*26 -> 4669.9973
K21: Tesla Premium Connect... | L21: =N21/26 -> 4.6107692 | M21: 9.99 | N21: =M21*12 -> 119.88
K22: Ford Ranger Fuel | L22: =N22/26 -> 34.615385 | M22: 75 | N22: =M22*12 -> 900
K23: Google Cloud | L23: =N23/26 -> 1.38 | M23: 2.99 | N23: =M23*12 -> 35.88
K24: Tess Hair | L24: =N24/26 -> 115.38462 | M24: 250 | N24: =M24*12 -> 3000
K25: Dog food | L25: =102.6/6*2 -> 34.2 | M25: =N25/12 -> 74.1 | N25: =L25*26 -> 889.2
K26: Dog grooming | L26: =360 / 6 * 2 -> 120 | M26: =N26/12 -> 260 | N26: =L26*26 -> 3120
K27: YouTube Premium | L27: =N27/26 -> 10.610769 | M27: 22.99 | N27: =M27*12 -> 275.88
K28: Excalidraw | L28: =N28/26 -> 5.1507692 | M28: 11.16 | N28: =M28*12 -> 133.92
K29: Apple TV+ | L29: =N29/26 -> 7.38 | M29: 15.99 | N29: =M29*12 -> 191.88
L30: =N30/26 -> 0 | M30: 0 | N30: =M30*12 -> 0
A35: Total Expenses | B35: =SUM(B3:B33) -> 1631.5385 | C35: =SUM(C3:C33) -> 3535 | D35: =SUM(D3:D33) -> 42420 | F35: Total Expenses | G35: =SUM(G3:G33) -> 2943.2308 | H35: =SUM(H3:H33) -> 6377 | I35: =SUM(I3:I33) -> 76524 | K35: Total Expenses | L35: =SUM(L3:L33) -> 1731.7571 | M35: =SUM(M3:M33) -> 3761.7138 | N35: =SUM(N3:N33) -> 45104.686 | P35: Total Expenses | Q35: =SUM(Q3:Q33) -> 362.76923 | R35: =SUM(R3:R33) -> 786 | S35: =SUM(S3:S33) -> 9432 | U35: Total Expenses | V35: =SUM(V3:V33) -> 38.615385 | W35: =SUM(W3:W33) -> 83.666667 | X35: =SUM(X3:X33) -> 1004
A38: Expense Total | B38: =B35+G35+L35+Q35+V35 -> 6707.911 | C38: =W35+R35+M35+C35+H35 -> 14543.38 | D38: =X35+S35+N35+D35+I35 -> 174484.69
A39: Income Total | B39: =Income!B6+Income!G6 -> 7873.0823 | C39: =Income!C6+Income!H6 -> 17058.345 | D39: =Income!D6+Income!I6 -> 204700.14
A40: Savings Total | B40: =B39-B38 -> 1165.1713 | C40: =C39-C38 -> 2514.9645 | D40: =D39-D38 -> 30215.454

Sheet Savings Schedule
A1: Date | B1: =TODAY() -> 46244 | C1: =B1+7*4 -> 46272 | D1: =C1+7*4 -> 46300 | E1: =D1+7*4 -> 46328 | F1: =E1+7*4 -> 46356 | G1: =F1+7*4 -> 46384 | H1: =G1+7*4 -> 46412 | I1: =H1+7*4 -> 46440 | J1: =I1+7*4 -> 46468 | ... O1: =N1+7*4 -> 46608
A2: Savings | B2: =103662 -> 103662 | C2: =B2+Expenses!$C40 -> 106176.96 | D2: =C2+Expenses!$C40 -> 108691.93 | E2: =D2+Expenses!$C40 -> 111206.89 | F2: =E2+Expenses!$C40 -> 113721.86 | G2: =F2+Expenses!$C40 -> 116236.82 | H2: =G2+Expenses!$C40 -> 118751.79 | I2: =H2+Expenses!$C40 -> 121266.75 | J2: =I2+Expenses!$C40 -> 123781.72 | ... O2: =N2+Expenses!$C40 -> 136356.54

Sheet Income
A1: Sam | F1: Tess
A2: Income | B2: Fortnight | C2: Month | D2: Year | F2: Income | G2: Fortnight | H2: Month | I2: Year
A3: Salary | B3: 5477.85 | C3: =D3/12 -> 11868.675 | D3: =B3*26 -> 142424.1 | F3: Salary | G3: =H3*12/26 -> 2395.2323 | H3: 5189.67 | I3: =G3*26 -> 62276.04
A6: Total | B6: =B3 -> 5477.85 | C6: =C3 -> 11868.675 | D6: =D3 -> 142424.1 | F6: Total | G6: =SUM(G3:G5) -> 2395.2323 | H6: =SUM(H3:H5) -> 5189.67 | I6: =SUM(I3:I5) -> 62276.04

Sheet Transaction History
A1: Date | B1: Description | C1: Inoive / Receipt Description | D1: Amount (AUD) | E1: Group | F1: Frequency | G1: Priority | H1: Notes
A2: 46240 | B2: BCC RATES & OTHER PYMT BRISBANE AUS | D2: 623.8 | E2: Brisbane City Council rates | F2: One-off | G2: Must Have
A3: 46240 | B3: FOREIGN FEE AUD 1.09 | D3: 1.09 | E3: Foreign transaction fees | F3: Recurring | G3: Fix | H3: Move USD subs to no-FX card
A4: 46240 | B4: ARCHITECTGPT MIAMI USA | D4: 37.75 | E4: ArchitectGPT | F4: One-off | G4: Nice to Have
A5: 46240 | B5: DBS*Brighton YMCA Spring Hill AUS | D5: 32.08 | E5: Brighton YMCA | F5: One-off | G5: Should Have
A6: 46239 | B6: PAYPAL *APPLE.COM/BILL AUS | C6: heyu | D6: 8.99 | E6: Apple | F6: Recurring | G6: Nice to Have | H6: Find Gmail invoice
A7: 46239 | B7: PAYPAL *UBER AU AUS | D7: 43.19 | E7: Uber rides | F7: Recurring | G7: Should Have
A8: 46239 | B8: FOREIGN FEE AUD 0.74 | D8: 0.74 | E8: Foreign transaction fees | F8: Recurring | G8: Fix | H8: Move USD subs to no-FX card
A9: 46239 | B9: VERCEL MKT NEON COVINA USA | D9: 25.58 | E9: Vercel | F9: Recurring | G9: Nice to Have
A10: 46239 | B10: PAYPAL *PYPL Payin4 AUS | C10: KZEMOS AUSTRALIA PTY LTD | D10: 55.13 | E10: Candlelight concert | F10: One-off | G10: Nice to Have
A11: 46239 | B11: PAYPAL *LUCENTGLOBE LU AUS | D11: 56.29 | E11: Household Supplies | F11: Recurring | G11: Should Have
A12: 46238 | B12: AVERON EXPRESS PTY LTD SANDGATE AUS | D12: 185.68 | E12: Averon Express | F12: One-off | G12: Must Have
A13: 46238 | B13: LINKT BRISBANE BRISBANE AUS | D13: 20.2 | E13: Linkt tolls | F13: Recurring | G13: Nice to Have
A14: 46238 | B14: DBS*KC Sandgate Pty Lt Sandgate AUS | D14: 291.3 | E14: KC Sandgate | F14: Recurring | G14: Must Have
A15: 46238 | B15: SUDS AND SEEDS BRISBANE AUS | D15: 123.06 | E15: Suds and Seeds | F15: One-off | G15: Should Have
A16: 46238 | B16: ESPRESSO VELOCE Brisbane AUS | D16: 10.19 | E16: ESPRESSO VELOCE BRISBANE | F16: One-off | G16: Nice to Have
A17: 46237 | B17: AMAZON AU MARKETPLACE SYDNEY AUS | C17: Treadmill | D17: 191.37 | E17: Amazon AU | F17: One-off | G17: Nice to Have | H17: Find Gmail invoice
A18: 46236 | B18: AMAZON WEB SERVICES SYDNEY AUS | D18: 0.83 | E18: AWS | F18: Recurring | G18: Nice to Have
A19: 46236 | B19: Google Workspace_rekur Sydney AUS | D19: 25.96 | E19: Google Workspace (Rekurve) | F19: Recurring | G19: Nice to Have
A20: 46235 | B20: PAYPAL *PYPL Payin4 AUS | C20: Nobita Trading Co Ltd. | D20: 67.5 | E20: Vehicle Maintenance | F20: One-off | G20: Nice to Have | H20: Head unit upgrade
A21: 46235 | B21: PAYPAL *UBEREATS AU AUS | D21: 65.27 | E21: UberEats | F21: Recurring | G21: Nice to Have
A22: 46235 | B22: FOREIGN FEE AUD 10.20 | D22: 10.2 | E22: Foreign transaction fees | F22: Recurring | G22: Fix | H22: Move USD subs to no-FX card
A23: 46235 | B23: ANTHROPIC* CLAUDE SUB SAN FRANCIS USA | D23: 350.2 | E23: Anthropic / Claude | F23: Recurring | G23: Should Have
A24: 46235 | B24: LINKT BRISBANE BRISBANE AUS | D24: 20.2 | E24: Linkt tolls | F24: Recurring | G24: Nice to Have
A25: 46235 | B25: TFNSW OPAL FARE SYDNEY AUS | D25: 21.64 | E25: Public transport | F25: One-off | G25: Should Have
A26: 46234 | B26: AMAZON AU MARKETPLACE SYDNEY AUS | C26: Weighted vest | D26: 65.99 | E26: Amazon AU | F26: One-off | G26: Nice to Have | H26: Find Gmail invoice
A27: 46234 | B27: TFNSW OPAL FARE SYDNEY AUS | D27: 21.64 | E27: Public transport | F27: One-off | G27: Should Have
A28: 46234 | B28: FOREIGN FEE AUD 0.90 | D28: 0.9 | E28: Foreign transaction fees | F28: Recurring | G28: Fix | H28: Move USD subs to no-FX card
A29: 46234 | B29: OPENAI *CHATGPT SUBSCR SAN FRANCIS USA | D29: 30.9 | E29: OpenAI ChatGPT | F29: One-off | G29: Nice to Have
A30: 46234 | B30: Loop Bagels MASCOT AUS | D30: 23.37 | E30: LOOP BAGELS MASCOT | F30: One-off | G30: Nice to Have
A31: 46233 | B31: DBS*Brighton YMCA Spring Hill AUS | D31: 48.13 | E31: Brighton YMCA | F31: One-off | G31: Should Have
A32: 46233 | B32: UBER *TRIP HELP.UBER.C Sydney AUS | D32: 15.26 | E32: Uber rides | F32: Recurring | G32: Should Have
A33: 46233 | B33: SQ *HUB WYNYARD PTY LT Sydney AUS | D33: 6.5 | E33: HUB WYNYARD PTY LT SYDNEY | F33: One-off | G33: Nice to Have
A34: 46233 | B34: UBER *EATS HELP.UBER.C Sydney AUS | D34: 125.19 | E34: UberEats | F34: Recurring | G34: Nice to Have
A35: 46232 | B35: PAYPAL *APPLE.COM/BILL AUS | C35: Unfold: Story & Reels Maker + heyu | D35: 13.48 | E35: Apple | F35: Recurring | G35: Nice to Have | H35: Find Gmail invoice
A36: 46232 | B36: FOREIGN FEE AUD 0.86 | D36: 0.86 | E36: Foreign transaction fees | F36: Recurring | G36: Fix | H36: Move USD subs to no-FX card
A37: 46232 | B37: VERCEL INC. COVINA USA | D37: 29.76 | E37: Vercel | F37: Recurring | G37: Nice to Have
A38: 46231 | B38: PAYPAL *APPLE.COM/BILL AUS | C38: iCloud+ 2TB | D38: 14.99 | E38: Apple | F38: Recurring | G38: Should Have | H38: Find Gmail invoice
A39: 46231 | B39: PAYPAL *APPLE.COM/BILL AUS | C39: Apple One Individual | D39: 24.95 | E39: Apple | F39: Recurring | G39: Nice to Have | H39: Find Gmail invoice
A40: 46231 | B40: DBS*KC Sandgate Pty Lt Sandgate AUS | D40: 271.85 | E40: KC Sandgate | F40: Recurring | G40: Must Have
A41: 46231 | B41: CIRCUM AMUSEMENTS MENTONE AUS | D41: 4.3 | E41: CIRCUM AMUSEMENTS MENTONE | F41: One-off | G41: Nice to Have
A42: 46231 | B42: CIRCUM AMUSEMENTS MENTONE AUS | D42: 4.3 | E42: CIRCUM AMUSEMENTS MENTONE | F42: One-off | G42: Nice to Have
A43: 46231 | B43: Microsoft-G173755134 Sydney AUS | D43: 13.86 | E43: Microsoft | F43: One-off | G43: Nice to Have
A44: 46230 | B44: PAYPAL *BUPAHIPTYLT AUS | D44: 194.32 | E44: Bupa health insurance | F44: Recurring | G44: Must Have
A45: 46230 | B45: FOREIGN FEE AUD 5.06 | D45: 5.06 | E45: Foreign transaction fees | F45: Recurring | G45: Fix | H45: Move USD subs to no-FX card
A46: 46230 | B46: PAYPAL *TSINLONETWO TS HKG | C46: Tess Clothing | D46: 174.03 | E46: Clothing | F46: One-off | G46: Should Have
A47: 46230 | B47: FOREIGN FEE AUD 2.27 | D47: 2.27 | E47: Foreign transaction fees | F47: Recurring | G47: Fix | H47: Move USD subs to no-FX card
A48: 46230 | B48: 1PASSWORD TORONTO CAN | D48: 78.13 | E48: 1Password | F48: One-off | G48: Nice to Have
A49: 46230 | B49: PET INSURANCE PETSUR CHATSWOOD AUS | D49: 82.9 | E49: Pet insurance | F49: Recurring | G49: Should Have
A50: 46229 | B50: PAYPAL *APPLE.COM/BILL AUS | C50: Paramount+ | D50: 12.99 | E50: Apple | F50: Recurring | G50: Nice to Have | H50: Find Gmail invoice
A51: 46229 | B51: PAYPAL *UBEREATS AU AUS | D51: 16.78 | E51: UberEats | F51: Recurring | G51: Nice to Have
A52: 46228 | B52: PAYPAL *PYPL Payin4 AUS | C52: Western Air Cleaner Services Pty Ltd | D52: 37.41 | E52: Vehicle Maintenance | F52: One-off | G52: Must Have
A53: 46228 | B53: PAYPAL *APPLE.COM/BILL AUS | C53: iCloud+ 2TB | D53: 14.99 | E53: Apple | F53: Recurring | G53: Should Have | H53: Find Gmail invoice
A54: 46228 | B54: PAYPAL *UBEREATS AU AUS | D54: 45.92 | E54: UberEats | F54: Recurring | G54: Nice to Have
A55: 46228 | B55: PAYPAL *DISNEYPLUS AUS | D55: 17.99 | E55: Disney+ | F55: Recurring | G55: Nice to Have
A56: 46228 | B56: LINKT BRISBANE BRISBANE AUS | D56: 20.2 | E56: Linkt tolls | F56: Recurring | G56: Nice to Have
A57: 46228 | B57: SP GRUNT 4X4 HALLAM AUS | D57: 261.53 | E57: 4WD / auto parts | F57: One-off | G57: Should Have
A58: 46228 | B58: AUTOBARN VIRGINIA VIRGINIA AUS | D58: 109.97 | E58: 4WD / auto parts | F58: One-off | G58: Should Have
A59: 46227 | B59: SP WILD AUTO PARTS BUNYIP AUS | D59: 68.95 | E59: 4WD / auto parts | F59: One-off | G59: Should Have
A60: 46226 | B60: QUEENSLAND URBAN UTI FORTITUDE V AUS | D60: 422.12 | E60: QLD Urban Utilities (water) | F60: One-off | G60: Must Have
A61: 46225 | B61: PAYPAL *APPLE.COM/BILL AUS | C61: AppleCare | D61: 8.49 | E61: Apple | F61: Recurring | G61: Should Have | H61: Find Gmail invoice
A62: 46225 | B62: PAYPAL *PYPL Payin4 AUS | C62: KZEMOS AUSTRALIA PTY LTD | D62: 55.12 | E62: Candlelight concert | F62: One-off | G62: Nice to Have
A63: 46224 | B63: PAYPAL *PYPL Payin4 AUS | C63: Jefferson Ford Pty Ltd | D63: 44.81 | E63: Vehicle Maintenance | F63: One-off | G63: Nice to Have | H63: Find Gmail invoice
A64: 46224 | B64: DBS*KC Sandgate Pty Lt Sandgate AUS | D64: 272.05 | E64: KC Sandgate | F64: Recurring | G64: Must Have
A65: 46224 | B65: DBS*KC Sandgate Pty Lt Sandgate AUS | D65: 375.27 | E65: KC Sandgate | F65: Recurring | G65: Must Have
A66: 46223 | B66: AMAZON AU MARKETPLACE SYDNEY AUS | D66: 44.39 | E66: Vehicle Maintenance | F66: One-off | G66: Nice to Have | H66: Find Gmail invoice
A67: 46223 | B67: QT CLINICS PTY LTD MEREWETHER AUS | D67: 238.89 | E67: QT Clinics | F67: One-off | G67: Must Have
A68: 46222 | B68: OVO ENERGY PTY LTD MELBOURNE AUS | D68: 400.45 | E68: OVO Energy | F68: Recurring | G68: Must Have
A69: 46222 | B69: ALLIANZ AUSTRALIA INSU SYDNEY AUS | D69: 223.95 | E69: Allianz insurance | F69: Recurring | G69: Must Have
A70: 46222 | B70: PAYPAL *PYPL Payin4 AUS | C70: Nobita Trading Co Ltd. | D70: 67.5 | E70: Vehicle Maintenance | F70: One-off | G70: Nice to Have | H70: Head unit upgrade
A71: 46222 | B71: PAYPAL *UBEREATS AU AUS | D71: 100.98 | E71: UberEats | F71: Recurring | G71: Nice to Have
A72: 46222 | B72: PAYPAL *UBER AU AUS | D72: 9.99 | E72: Uber rides | F72: Recurring | G72: Should Have
A73: 46221 | B73: AMAZON AU RETAIL SYDNEY AUS | C73: Batteries | D73: 20.27 | E73: Home Maintenance | F73: One-off | G73: Should Have
A74: 46221 | B74: C34713 TFR FROM Westpa c Choice | D74: 0 | E74: CARD PAYMENT | G74: n/a | H74: Card payment (not spend)
A75: 46220 | B75: AGL SALES 0308 MELBOURNE AUS | D75: 62.06 | E75: AGL | F75: Recurring | G75: Must Have
A76: 46219 | B76: FOREIGN FEE AUD 0.56 | D76: 0.56 | E76: Foreign transaction fees | F76: Recurring | G76: Fix | H76: Move USD subs to no-FX card
A77: 46219 | B77: PAYPAL *GAIA GAIA INC. USA | D77: 19.55 | E77: Gaia | F77: Recurring | G77: Nice to Have
A78: 46219 | B78: SMP*EW Cosmetic Injec9 Lawnton AUS | D78: 494.62 | E78: Beauty / body / wellness | F78: Recurring | G78: Should Have
A79: 46219 | B79: PAYPAL *STAN AUS | D79: 23.99 | E79: Stan | F79: One-off | G79: Nice to Have
A80: 46219 | B80: PAYPAL *TEAM BBR TEAM AUS | D80: 24.99 | E80: TEAM BBR TEAM | F80: One-off | G80: Nice to Have
A81: 46219 | B81: 4 PAWS DOG GROOMERS SANDGATE AUS | D81: 451.9 | E81: Pets | F81: Recurring | G81: Should Have
A82: 46219 | B82: ZLR*Level 10 The Studi teneriffe AUS | D82: 505.83 | E82: Beauty / body / wellness | F82: Recurring | G82: Should Have
A83: 46218 | B83: PAYPAL *APPLE.COM/BILL AUS | C83: YoutTube + heyu + Magic faraway tree | D83: 38.97 | E83: Apple | F83: Recurring | G83: Nice to Have | H83: Find Gmail invoice
A84: 46218 | B84: FOREIGN FEE AUD 0.30 | D84: 0.3 | E84: Foreign transaction fees | F84: Recurring | G84: Fix | H84: Move USD subs to no-FX card
A85: 46218 | B85: PLUS.EXCALIDRAW.COM BRNO CZE | D85: 10.43 | E85: Excalidraw Plus | F85: Recurring | G85: Nice to Have
A86: 46217 | B86: PAYPAL *SPOTIFY*P4496E AUS | D86: 20.99 | E86: Spotify | F86: Recurring | G86: Must Have
A87: 46217 | B87: PAYPAL *WAVES AU 0400532664 AUS | D87: 140 | E87: WAVES AU | F87: One-off | G87: Nice to Have
A88: 46217 | B88: PAYPAL *NETFLIX AUS AUS | D88: 20.99 | E88: Netflix | F88: Recurring | G88: Nice to Have
A89: 46217 | B89: PAYPAL *GOOGLE GOOGLE AUS | D89: 2.99 | E89: Google One/Play | F89: Recurring | G89: Should Have
A90: 46216 | B90: Tesla Inc St Leonards AUS | D90: 13.99 | E90: Tesla supercharging | F90: Recurring | G90: Must Have
A91: 46215 | B91: PAYPAL *PETBARN AUS | D91: 99.9 | E91: Pets | F91: Recurring | G91: Should Have
A92: 46214 | B92: PAYPAL *PYPL Payin4 AUS | C92: Western Air Cleaner Services Pty Ltd | D92: 37.41 | E92: Vehicle Maintenance | F92: One-off | G92: Must Have
A93: 46214 | B93: PAYPAL *UBEREATS AU AUS | D93: 36.08 | E93: UberEats | F93: Recurring | G93: Nice to Have
A94: 46214 | B94: LINKT BRISBANE BRISBANE AUS | D94: 20.2 | E94: Linkt tolls | F94: Recurring | G94: Nice to Have
A95: 46213 | B95: PAYPAL *UBER AU AUS | D95: 26.44 | E95: Uber rides | F95: Recurring | G95: Should Have
A96: 46213 | B96: LINKT BRISBANE BRISBANE AUS | D96: 20.2 | E96: Linkt tolls | F96: Recurring | G96: Nice to Have
A97: 46213 | B97: Hubbl - BINGE Artarmon AUS | D97: 19 | E97: Binge (Hubbl) | F97: Recurring | G97: Nice to Have
A98: 46212 | B98: PAYPAL *APPLE.COM/BILL AUS | C98: Binge Standard | D98: 19 | E98: Apple | F98: Recurring | G98: Nice to Have | H98: Find Gmail invoice
A99: 46212 | B99: WESTFIELD CHERMSIDE CHERMSIDE AUS | D99: 4 | E99: WESTFIELD CHERMSIDE CHERMSIDE | F99: One-off | G99: Nice to Have
A100: 46212 | B100: LINKT BRISBANE BRISBANE AUS | D100: 20.2 | E100: Linkt tolls | F100: Recurring | G100: Nice to Have
...

Sheet Wishlist
A1: Name | B1: Store / Link | C1: Notes | D1: Cost | E1: Tess | F1: Sam | G1: Priority | H1: Category
A2: Ranger - Injector Replacement | B2: https://drive.google.com/file/d/1Gg1XMyR5ErJG2pxi6IKwILfrsozb6fZj/view?usp=sharing | C2: Required maintenance - Injectors will fail within the next 30,000km. | D2: 3420.89 | E2: Must Have | F2: Must Have | G2: =IFERROR(vlookup(E2,Data!$A$2:$B$4,2,0), 0) + IFERROR(vlookup(F2,Data!$A$2:$B$4,2,0), 0) -> 4 | H2: Vehicle
A3: Ranger - Turbo Upgrade/Replacement | B3: https://gturbo.com.au/product/turbo-fr-g300-vortex-gold-px1/ | C3: Better Towing performance | D3: 3290 | E3: Nice to Have | F3: Must Have | G3: =IFERROR(vlookup(E3,Data!$A$2:$B$4,2,0), 0) + IFERROR(vlookup(F3,Data!$A$2:$B$4,2,0), 0) -> 3 | H3: Vehicle
A4: Kitchen Stools | B4: https://www.loungelovers.com.au/arabelle-74cm-bar-stool-walnut | D4: =149 * 3 -> 447 | E4: Nice to Have | F4: Nice to Have | G4: =IFERROR(vlookup(E4,Data!$A$2:$B$4,2,0), 0) + IFERROR(vlookup(F4,Data!$A$2:$B$4,2,0), 0) -> 2 | H4: House
A5: 2 x Bean bags for theatre | B5: https://www.etsy.com/au/listing/1174140933/textured-linen-bean-bag-cover | C5: Seating for kids | D5: 240 | E5: Nice to Have | F5: Nice to Have | G5: =IFERROR(vlookup(E5,Data!$A$2:$B$4,2,0), 0) + IFERROR(vlookup(F5,Data!$A$2:$B$4,2,0), 0) -> 2 | H5: Furniture
A6: Ranger Head Unit/Screen | B6: Polaris Universal Maxx | C6: Reverse Camera & Apple Car Play | D6: 895 | E6: Purchased | F6: Purchased | G6: =IFERROR(vlookup(E6,Data!$A$2:$B$4,2,0), 0) + IFERROR(vlookup(F6,Data!$A$2:$B$4,2,0), 0) -> 0 | H6: Vehicle
A7: Awning Ensuite for the Ute | B7: https://caosgear.com.au/products/nomad-shower-tent-awning-foldout-with-roof | C7: Awning ensuite of privacy when showering, using the toilet, or simply changing clothes after a swim in a public place. | D7: =289 -> 289 | E7: Purchased | F7: Purchased | G7: =IFERROR(vlookup(E7,Data!$A$2:$B$4,2,0), 0) + IFERROR(vlookup(F7,Data!$A$2:$B$4,2,0), 0) -> 0 | H7: Camping
A8: Awning Ensuite Shower Floor for the Ute | B8: https://www.kickassproducts.com.au/buy/shower-base-for-awning/KASTENT-BASE | C8: Awning ensuite shower floor to keep feet clean during a shower. | D8: =99 -> 99 | E8: Purchased | F8: Purchased | G8: =IFERROR(vlookup(E8,Data!$A$2:$B$4,2,0), 0) + IFERROR(vlookup(F8,Data!$A$2:$B$4,2,0), 0) -> 0 | H8: Camping
A9: Bedside tables | D9: 500 | E9: Purchased | F9: Purchased | G9: =IFERROR(vlookup(E9,Data!$A$2:$B$4,2,0), 0) + IFERROR(vlookup(F9,Data!$A$2:$B$4,2,0), 0) -> 0
G10: 0
G11: 0
G12: 0
G13: 0
G14: 0
G15: 0
G16: 0
G17: =IFERROR(vlookup(E17,Data!$A$2:$B$4,2,0), 0) + IFERROR(vlookup(F17,Data!$A$2:$B$4,2,0), 0) -> 0
G18: =IFERROR(vlookup(E18,Data!$A$2:$B$4,2,0), 0) + IFERROR(vlookup(F18,Data!$A$2:$B$4,2,0), 0) -> 0
G19: =IFERROR(vlookup(E19,Data!$A$2:$B$4,2,0), 0) + IFERROR(vlookup(F19,Data!$A$2:$B$4,2,0), 0) -> 0
G20: =IFERROR(vlookup(E20,Data!$A$2:$B$4,2,0), 0) + IFERROR(vlookup(F20,Data!$A$2:$B$4,2,0), 0) -> 0
G21: =IFERROR(vlookup(E21,Data!$A$2:$B$4,2,0), 0) + IFERROR(vlookup(F21,Data!$A$2:$B$4,2,0), 0) -> 0
G22: =IFERROR(vlookup(E22,Data!$A$2:$B$4,2,0), 0) + IFERROR(vlookup(F22,Data!$A$2:$B$4,2,0), 0) -> 0
G23: =IFERROR(vlookup(E23,Data!$A$2:$B$4,2,0), 0) + IFERROR(vlookup(F23,Data!$A$2:$B$4,2,0), 0) -> 0
G24: =IFERROR(vlookup(E24,Data!$A$2:$B$4,2,0), 0) + IFERROR(vlookup(F24,Data!$A$2:$B$4,2,0), 0) -> 0
G25: =IFERROR(vlookup(E25,Data!$A$2:$B$4,2,0), 0) + IFERROR(vlookup(F25,Data!$A$2:$B$4,2,0), 0) -> 0
G26: =IFERROR(vlookup(E26,Data!$A$2:$B$4,2,0), 0) + IFERROR(vlookup(F26,Data!$A$2:$B$4,2,0), 0) -> 0
G27: =IFERROR(vlookup(E27,Data!$A$2:$B$4,2,0), 0) + IFERROR(vlookup(F27,Data!$A$2:$B$4,2,0), 0) -> 0
G28: =IFERROR(vlookup(E28,Data!$A$2:$B$4,2,0), 0) + IFERROR(vlookup(F28,Data!$A$2:$B$4,2,0), 0) -> 0
... G957: =IFERROR(vlookup(E957,Data!$A$2:$B$4,2,0), 0) + IFERROR(vlookup(F957,Data!$A$2:$B$4,2,0), 0) -> 0

Sheet Data
B1: Weight
A2: Urgent | B2: 3
A3: Must Have | B3: 2
A4: Nice to Have | B4: 1
A5: Unnecessary | B5: 0
A6: Purchased | B6: 0
